mdformat_deflist/__init__.py
mdformat_deflist/plugin.py
mdformat_deflist-0.1.4.dist-info/entry_points.txt
mdformat_deflist-0.1.4.dist-info/licenses/LICENSE
mdformat_deflist-0.1.4.dist-info/WHEEL
mdformat_deflist-0.1.4.dist-info/METADATA
mdformat_deflist-0.1.4.dist-info/RECORD
