Metadata-Version: 2.4
Name: mdformat_deflist
Version: 0.1.4
Summary: An mdformat plugin for markdown-it-deflist.
Home-page: https://github.com/executablebooks/mdformat-deflist
Keywords: mdformat,markdown,markdown-it
Author: Chris Sewell
Author-email: executablebooks@gmail.com
Requires-Python: >=3.10
Classifier: Intended Audience :: Developers
Classifier: License :: OSI Approved :: MIT License
Classifier: Programming Language :: Python :: 3
Classifier: Topic :: Software Development :: Libraries :: Python Modules
License-File: LICENSE
Requires-Dist: mdformat >=1.0.0
Requires-Dist: mdit-py-plugins >=0.2.7
Requires-Dist: pre-commit ; extra == "dev"
Requires-Dist: pytest>=8.0.0 ; extra == "test"
Requires-Dist: pytest-cov>=7.0.0 ; extra == "test"
Provides-Extra: dev
Provides-Extra: test
